Utils/Mongo_conn.py
Utils/MyUtils.py
Utils/Rabbit_conn.py
Utils/Redis_conn.py
Utils/__init__.py
Utils/get_proxy.py
Utils/monitor_rabbit.py
zlkj-0.1.0.dist-info/LICENSE
zlkj-0.1.0.dist-info/METADATA
zlkj-0.1.0.dist-info/WHEEL
zlkj-0.1.0.dist-info/top_level.txt
zlkj-0.1.0.dist-info/RECORD
